{"cameraMode":{"drawMode":0,"name":"Shaded","section":"Shading Mode"},"sceneLighting":true,"audioPlay":false,"sceneViewState":{"m_AlwaysRefresh":false,"showFog":true,"showSkybox":true,"showFlares":true,"showImageEffects":true,"showParticleSystems":true,"showVisualEffectGraphs":true,"m_FxEnabled":true},"in2DMode":false,"pivot":{"x":1.2719305753707886,"y":7.435043811798096,"z":-2.2573957443237306},"rotation":{"x":0.25815916061401369,"y":-0.07382071763277054,"z":0.019787821918725969,"w":0.9630831480026245},"size":-4.799144744873047,"orthographic":false}